sayari/__init__.py
sayari/attributes/__init__.py
sayari/attributes/client.py
sayari/attributes/types/__init__.py
sayari/attributes/types/add_attribute.py
sayari/attributes/types/attribute_properties.py
sayari/attributes/types/attribute_response.py
sayari/attributes/types/attribute_response_data.py
sayari/attributes/types/update_attribute.py
sayari/auth/__init__.py
sayari/auth/client.py
sayari/auth/types/__init__.py
sayari/auth/types/auth_response.py
sayari/base_client.py
sayari/base_types/__init__.py
sayari/base_types/types/__init__.py
sayari/base_types/types/count_qualifier.py
sayari/base_types/types/custom_field_value.py
sayari/base_types/types/paginated_response.py
sayari/base_types/types/qualified_count.py
sayari/client.py
sayari/core/__init__.py
sayari/core/api_error.py
sayari/core/client_wrapper.py
sayari/core/datetime_utils.py
sayari/core/file.py
sayari/core/http_client.py
sayari/core/jsonable_encoder.py
sayari/core/oauth_token_provider.py
sayari/core/pydantic_utilities.py
sayari/core/query_encoder.py
sayari/core/remove_none_from_dict.py
sayari/core/request_options.py
sayari/core/serialization.py
sayari/entity/__init__.py
sayari/entity/client.py
sayari/entity/types/__init__.py
sayari/entity/types/entity_summary_response.py
sayari/entity/types/get_entity_response.py
sayari/environment.py
sayari/generated_types/__init__.py
sayari/generated_types/types/__init__.py
sayari/generated_types/types/additional_information_data.py
sayari/generated_types/types/additional_information_info.py
sayari/generated_types/types/additional_information_properties.py
sayari/generated_types/types/address_data.py
sayari/generated_types/types/address_info.py
sayari/generated_types/types/address_properties.py
sayari/generated_types/types/address_type.py
sayari/generated_types/types/attribute_data.py
sayari/generated_types/types/attribute_details.py
sayari/generated_types/types/attributes.py
sayari/generated_types/types/both_identifier_types.py
sayari-0.1.42.dist-info/METADATA
sayari-0.1.42.dist-info/WHEEL
sayari-0.1.42.dist-info/RECORD
